plus_sync/__init__.py
plus_sync/__version__.py
plus_sync/hashing.py
plus_sync/py.typed
plus_sync/cmd/__init__.py
plus_sync/cmd/app.py
plus_sync/cmd/commands/__init__.py
plus_sync/cmd/commands/init.py
plus_sync/cmd/commands/list_remotes.py
plus_sync/cmd/commands/list_subjects.py
plus_sync/cmd/commands/ls.py
plus_sync/cmd/commands/sync.py
plus_sync/cmd/helpers/__init__.py
plus_sync/cmd/helpers/decorators.py
plus_sync/cmd/helpers/options.py
plus_sync/cmd/helpers/typer.py
plus_sync/cmd/subcommands/__init__.py
plus_sync/cmd/subcommands/add.py
plus_sync/config/__init__.py
plus_sync/config/abstract.py
plus_sync/config/config.py
plus_sync/config/helpers.py
plus_sync/pytest/__init__.py
plus_sync/pytest/plugin.py
plus_sync/pytest/factories/__init__.py
plus_sync/pytest/factories/subject_file.py
plus_sync/sync/__init__.py
plus_sync/sync/base.py
plus_sync/sync/gitlab.py
plus_sync/sync/rclone.py
plus_sync/sync/sftp.py
plus_sync-0.7.3.dist-info/METADATA
plus_sync-0.7.3.dist-info/WHEEL
plus_sync-0.7.3.dist-info/entry_points.txt
plus_sync-0.7.3.dist-info/licenses/LICENSE
plus_sync-0.7.3.dist-info/RECORD
