Metadata-Version: 2.4
Name: plus_sync
Version: 0.7.3
Summary: Convenient command line tool to sync all kind of data.
Author-email: Thomas Hartmann <thomas.hartmann@th-ht.de>
License: GPL-3.0
License-File: LICENSE
Requires-Python: >=3.9
Requires-Dist: attrs-strict<2,>=1.0.1
Requires-Dist: attrs<26,>=25.3.0
Requires-Dist: cattrs<26,>=25.1.1
Requires-Dist: click
Requires-Dist: factory-boy<4,>=3.3.3
Requires-Dist: joblib<2,>=1.5.2
Requires-Dist: paramiko<5,>=4.0.0
Requires-Dist: python-gitlab<7,>=6.3.0
Requires-Dist: quickxorhash<2,>=1.0.5
Requires-Dist: tomlkit
Requires-Dist: tqdm<5,>=4.67.1
Requires-Dist: typer<0.17,>=0.16.1
